valkyrie/__init__.py
valkyrie/linear_model.py
valkyrie-0.0.1.dist-info/LICENSE
valkyrie-0.0.1.dist-info/METADATA
valkyrie-0.0.1.dist-info/WHEEL
valkyrie-0.0.1.dist-info/top_level.txt
valkyrie-0.0.1.dist-info/RECORD
